_pyodide/__init__.py
_pyodide/_base.py
_pyodide/_core_docs.py
_pyodide/_importhook.py
_pyodide/console.py
_pyodide/docstring.py
pyodide/__init__.py
pyodide/_core.py
pyodide/_state.py
pyodide/_util.py
pyodide/console.py
pyodide/http.py
pyodide/webloop.py
pyodide-0.19.0a1.dist-info/METADATA
pyodide-0.19.0a1.dist-info/WHEEL
pyodide-0.19.0a1.dist-info/top_level.txt
pyodide-0.19.0a1.dist-info/RECORD
