Metadata-Version: 2.1
Name: pyodide
Version: 0.19.0a1
Summary: "A Python package providing core interpreter functionality for Pyodide."
Home-page: https://github.com/pyodide/pyodide
Author: Pyodide developers
License: UNKNOWN
Project-URL: Bug Tracker, https://github.com/pyodide/pyodide/issues
Project-URL: Documentation, https://pyodide.org/en/stable/
Platform: UNKNOWN
Classifier: Programming Language :: Python :: 3
Classifier: License :: OSI Approved :: Mozilla Public License 2.0 (MPL 2.0)
Classifier: Operating System :: OS Independent
Requires-Python: >=3.8
